airbyte_protocol_dataclasses/models/__init__.py
airbyte_protocol_dataclasses/models/airbyte_protocol.py
airbyte_protocol_dataclasses/models/well_known_types.py
airbyte_protocol_models_dataclasses-0.18.0.dist-info/licenses/LICENSE.txt
airbyte_protocol_models_dataclasses-0.18.0.dist-info/METADATA
airbyte_protocol_models_dataclasses-0.18.0.dist-info/WHEEL
airbyte_protocol_models_dataclasses-0.18.0.dist-info/top_level.txt
airbyte_protocol_models_dataclasses-0.18.0.dist-info/RECORD
