Metadata-Version: 2.4
Name: airbyte_protocol_models_dataclasses
Version: 0.18.0
Summary: Declares the Airbyte Protocol using Python Dataclasses. Dataclasses in Python have less performance overhead compared to Pydantic models, making them a more efficient choice for scenarios where speed and memory usage are critical
Home-page: https://github.com/airbytehq/airbyte-protocol
Author: Airbyte
Author-email: contact@airbyte.io
License: MIT
Project-URL: Documentation, https://docs.airbyte.io/
Project-URL: Source, https://github.com/airbytehq/airbyte-protocol
Project-URL: Tracker, https://github.com/airbytehq/airbyte-protocol/issues
Keywords: airbyte airbyte-protocol
Classifier: Development Status :: 3 - Alpha
Classifier: Intended Audience :: Developers
Classifier: Topic :: Scientific/Engineering
Classifier: Topic :: Software Development :: Libraries :: Python Modules
Classifier: License :: OSI Approved :: MIT License
Classifier: Programming Language :: Python :: 3.11
Classifier: Programming Language :: Python :: 3.10
Classifier: Programming Language :: Python :: 3.9
Requires-Python: >=3.9
License-File: LICENSE.txt
Dynamic: author
Dynamic: author-email
Dynamic: classifier
Dynamic: description
Dynamic: description-content-type
Dynamic: home-page
Dynamic: keywords
Dynamic: license
Dynamic: license-file
Dynamic: project-url
Dynamic: requires-python
Dynamic: summary
